pyinstallerui/__init__.py
pyinstallerui/__main__.py
pyinstallerui/core.py
pyinstallerui-0.2.3.dist-info/LICENSE
pyinstallerui-0.2.3.dist-info/METADATA
pyinstallerui-0.2.3.dist-info/WHEEL
pyinstallerui-0.2.3.dist-info/top_level.txt
pyinstallerui-0.2.3.dist-info/RECORD
