Metadata-Version: 2.1
Name: pyinstallerui
Version: 0.2.3
Summary: Let everyone is able to build python script to exe with pyinstaller, without any doc reading, support python3.7+. Read more: https://github.com/ClericPy/pyinstallerui.
Home-page: https://github.com/ClericPy/pyinstallerui
Author: ClericPy
Author-email: clericpy@gmail.com
License: MIT License
Keywords: pyinstaller tui terminal ui gui
Platform: any
Classifier: License :: OSI Approved :: MIT License
Classifier: Programming Language :: Python :: 3
Classifier: Programming Language :: Python :: 3.7
Requires-Dist: questionary
